LIE/__init__.py
LIE/lang_tools/__init__.py
LIE/lang_tools/compFromMemory.py
LIE/lang_tools/compiler.py
LIE/lang_tools/LIEparser/__init__.py
LIE/lang_tools/LIEparser/parserErrorStrategy.py
LIE/lang_tools/LIEsemantic/__init__.py
LIE/lang_tools/LIEsemantic/semanticAnalyzer.py
LIE/lang_tools/LIEsemantic/semanticErrorStrategy.py
LIE/lang_tools/LIEsemantic/semanticErrors.py
LIE/lang_tools/analyzer/__init__.py
LIE/lang_tools/analyzer/codeAnalyzer.py
LIE/lang_tools/generator/__init__.py
LIE/lang_tools/generator/codeGenerator.py
LIE/lang_tools/multi/__init__.py
LIE/lang_tools/multi/multiFun.py
LIE-0.2.0.dist-info/LICENSE
LIE-0.2.0.dist-info/METADATA
LIE-0.2.0.dist-info/WHEEL
LIE-0.2.0.dist-info/top_level.txt
LIE-0.2.0.dist-info/RECORD
