Metadata-Version: 2.1
Name: LIE
Version: 0.2.0
Summary: A LIE++ to python compiler
Author: SoftLab
Author-email: 
License: MIT
Platform: UNKNOWN
License-File: LICENSE
Requires-Dist: antlr4-python3-runtime
Requires-Dist: lieGenTools
Requires-Dist: argparse
